README.rst
checktype.py
setup.py
checktype.egg-info/PKG-INFO
checktype.egg-info/SOURCES.txt
checktype.egg-info/dependency_links.txt
checktype.egg-info/top_level.txt