Metadata-Version: 1.1
Name: checktype
Version: 1.0.0
Summary: Intuitive and minimalistic type checking for Python objects
Home-page: https://github.com/renaud/checktype
Author: Renaud Richardet
Author-email: renaud@apache.org
License: Apache License (2.0)
Keywords: type checking
Platform: UNKNOWN
Classifier: Development Status :: 5 - Production/Stable
Classifier: Intended Audience :: Developers
Classifier: Topic :: Software Development :: Testing
Classifier: License :: OSI Approved :: Apache Software License
Classifier: Programming Language :: Python :: 2.6
Classifier: Programming Language :: Python :: 2.7
Classifier: Programming Language :: Python :: 3
Classifier: Programming Language :: Python :: 3.2
Classifier: Programming Language :: Python :: 3.3
Classifier: Programming Language :: Python :: 3.4
Classifier: Operating System :: OS Independent
Classifier: Environment :: Console
